magical/__init__.py
magical/__main__.py
magical/base_env.py
magical/entities.py
magical/evaluation.py
magical/geom.py
magical/gym_render.py
magical/phys_vars.py
magical/reference_demos.py
magical/saved_trajectories.py
magical/style.py
magical/version.py
magical/benchmarks/__init__.py
magical/benchmarks/cluster.py
magical/benchmarks/find_dupe.py
magical/benchmarks/fix_colour.py
magical/benchmarks/make_line.py
magical/benchmarks/match_regions.py
magical/benchmarks/move_to_corner.py
magical/benchmarks/move_to_region.py
magical/misc/__init__.py
magical/misc/benchmark_env_perf.py
magical/misc/convert_demos_to_new_act_format.py
magical/misc/re_record_demos.py
magical/misc/render_demos.py
magical/pyglet_backport/__init__.py
magical/pyglet_backport/image/__init__.py
magical/pyglet_backport/image/imagebuffer.py
magical_il-0.0.1a4.dist-info/LICENSE
magical_il-0.0.1a4.dist-info/METADATA
magical_il-0.0.1a4.dist-info/WHEEL
magical_il-0.0.1a4.dist-info/top_level.txt
magical_il-0.0.1a4.dist-info/RECORD
