Metadata-Version: 2.1
Name: magical-il
Version: 0.0.1a4
Summary: MAGICAL is a benchmark suite for robust imitation learning
Home-page: https://github.com/qxcv/magical/
Author: Sam Toyer
License: ISC
Platform: UNKNOWN
Requires-Python: >=3.6
Requires-Dist: pymunk (~=5.6.0)
Requires-Dist: pyglet (==1.5.*)
Requires-Dist: gym (==0.17.*)
Requires-Dist: Click (>=7.0)
Requires-Dist: numpy (>=1.17.4)
Requires-Dist: cloudpickle (>=1.2.2)
Requires-Dist: statsmodels (>=0.10.2)
Requires-Dist: requests (==2.*,>=2.20.0)
Requires-Dist: opencv-python-headless (==4.*)
Provides-Extra: dev
Requires-Dist: pytest (~=6.1.2) ; extra == 'dev'
Requires-Dist: pytest-xdist (~=2.1.0) ; extra == 'dev'
Requires-Dist: isort (~=5.0) ; extra == 'dev'
Requires-Dist: yapf (~=0.30.0) ; extra == 'dev'
Requires-Dist: flake8 (~=3.8.3) ; extra == 'dev'
Requires-Dist: autoflake (~=1.4) ; extra == 'dev'
Requires-Dist: pytest-flake8 (~=1.0.6) ; extra == 'dev'
Requires-Dist: pytest-isort (~=1.2.0) ; extra == 'dev'
